lxd_io/__init__.py
lxd_io/background_image_scale_factors.json
lxd_io/dataset.py
lxd_io/recording.py
lxd_io/track.py
lxd_io-0.4.10.dist-info/LICENSE
lxd_io-0.4.10.dist-info/METADATA
lxd_io-0.4.10.dist-info/WHEEL
lxd_io-0.4.10.dist-info/top_level.txt
lxd_io-0.4.10.dist-info/RECORD
