Metadata-Version: 2.1
Name: lxd_io
Version: 0.4.10
Summary: Read leveLXData datasets without boilerplate code
Author-email: Lennart Vater <lennart.vater@rwth-aachen.de>
Maintainer-email: Lennart Vater <lennart.vater@rwth-aachen.de>
License: MIT
Project-URL: Homepage, https://github.com/lenvt/lxd-io
Project-URL: Issues, https://github.com/lenvt/lxd-io/issues
Classifier: Development Status :: 4 - Beta
Classifier: Intended Audience :: Science/Research
Classifier: License :: OSI Approved :: MIT License
Classifier: Programming Language :: Python
Classifier: Topic :: Scientific/Engineering
Requires-Python: >=3.8
License-File: LICENSE
Requires-Dist: loguru >=0.7.3
Requires-Dist: matplotlib >=3.7.5
Requires-Dist: numpy >=1.23.4
Requires-Dist: polars >=1.8.2
